{
  "games": [
    {
      "id": "24729dddcfb49df9b718819c43d02af9",
      "sport": "MLB",
      "sport_key": "baseball_mlb",
      "home": "Boston Red Sox",
      "away": "Texas Rangers",
      "start_time": "2026-06-15T07:21:00+08:00",
      "commence_time_utc": "2026-06-14T23:21:00Z",
      "odds_h2h": [
        {
          "book": "fanduel",
          "home": 1.86,
          "away": 1.98,
          "draw": null
        },
        {
          "book": "betonlineag",
          "home": 1.88,
          "away": 2.04,
          "draw": null
        },
        {
          "book": "lowvig",
          "home": 1.88,
          "away": 2.04,
          "draw": null
        },
        {
          "book": "betus",
          "home": 1.88,
          "away": 2.03,
          "draw": null
        },
        {
          "book": "draftkings",
          "home": 1.85,
          "away": 1.98,
          "draw": null
        },
        {
          "book": "betmgm",
          "home": 1.85,
          "away": 1.98,
          "draw": null
        },
        {
          "book": "mybookieag",
          "home": 1.86,
          "away": 1.99,
          "draw": null
        },
        {
          "book": "bovada",
          "home": 1.84,
          "away": 1.99,
          "draw": null
        },
        {
          "book": "betrivers",
          "home": 1.83,
          "away": 1.97,
          "draw": null
        }
      ],
      "odds_totals": [
        {
          "book": "fanduel",
          "line": 9.0,
          "over": 1.87,
          "under": 1.95
        },
        {
          "book": "betonlineag",
          "line": 9.0,
          "over": 1.8,
          "under": 2.05
        },
        {
          "book": "lowvig",
          "line": 9.0,
          "over": 1.81,
          "under": 2.07
        },
        {
          "book": "betus",
          "line": 9.0,
          "over": 1.83,
          "under": 2.0
        },
        {
          "book": "draftkings",
          "line": 9.5,
          "over": 2.01,
          "under": 1.82
        },
        {
          "book": "betmgm",
          "line": 9.5,
          "over": 2.0,
          "under": 1.83
        },
        {
          "book": "mybookieag",
          "line": 9.0,
          "over": 1.83,
          "under": 1.98
        },
        {
          "book": "bovada",
          "line": 9.0,
          "over": 1.8,
          "under": 2.05
        },
        {
          "book": "betrivers",
          "line": 9.0,
          "over": 1.83,
          "under": 1.97
        }
      ],
      "odds_spreads": [
        {
          "book": "fanduel",
          "home_point": 1.5,
          "away_point": -1.5
        },
        {
          "book": "betonlineag",
          "home_point": -1.5,
          "away_point": 1.5
        },
        {
          "book": "lowvig",
          "home_point": -1.5,
          "away_point": 1.5
        },
        {
          "book": "betus",
          "home_point": -1.5,
          "away_point": 1.5
        },
        {
          "book": "draftkings",
          "home_point": 1.5,
          "away_point": -1.5
        },
        {
          "book": "betmgm",
          "home_point": 1.5,
          "away_point": -1.5
        },
        {
          "book": "mybookieag",
          "home_point": 1.5,
          "away_point": -1.5
        },
        {
          "book": "bovada",
          "home_point": -1.5,
          "away_point": 1.5
        },
        {
          "book": "betrivers",
          "home_point": 1.5,
          "away_point": -1.5
        }
      ]
    },
    {
      "id": "87cc10ad1f5377b838eb240a510a0f9f",
      "sport": "MLB",
      "sport_key": "baseball_mlb",
      "home": "Philadelphia Phillies",
      "away": "Miami Marlins",
      "start_time": "2026-06-16T06:41:00+08:00",
      "commence_time_utc": "2026-06-15T22:41:00Z",
      "odds_h2h": [
        {
          "book": "fanduel",
          "home": 1.48,
          "away": 2.76,
          "draw": null
        },
        {
          "book": "betonlineag",
          "home": 1.53,
          "away": 2.71,
          "draw": null
        },
        {
          "book": "lowvig",
          "home": 1.53,
          "away": 2.71,
          "draw": null
        },
        {
          "book": "betus",
          "home": 1.53,
          "away": 2.66,
          "draw": null
        },
        {
          "book": "betmgm",
          "home": 1.5,
          "away": 2.65,
          "draw": null
        },
        {
          "book": "draftkings",
          "home": 1.48,
          "away": 2.69,
          "draw": null
        },
        {
          "book": "bovada",
          "home": 1.47,
          "away": 2.73,
          "draw": null
        }
      ],
      "odds_totals": [
        {
          "book": "fanduel",
          "line": 7.5,
          "over": 1.88,
          "under": 1.94
        },
        {
          "book": "betonlineag",
          "line": 7.5,
          "over": 1.95,
          "under": 1.87
        },
        {
          "book": "lowvig",
          "line": 7.5,
          "over": 1.98,
          "under": 1.88
        },
        {
          "book": "betus",
          "line": 7.5,
          "over": 1.95,
          "under": 1.87
        },
        {
          "book": "betmgm",
          "line": 7.5,
          "over": 1.95,
          "under": 1.87
        },
        {
          "book": "draftkings",
          "line": 7.5,
          "over": 1.93,
          "under": 1.89
        },
        {
          "book": "bovada",
          "line": 7.5,
          "over": 1.91,
          "under": 1.91
        }
      ],
      "odds_spreads": [
        {
          "book": "fanduel",
          "home_point": -1.5,
          "away_point": 1.5
        },
        {
          "book": "betmgm",
          "home_point": -1.5,
          "away_point": 1.5
        },
        {
          "book": "draftkings",
          "home_point": -1.5,
          "away_point": 1.5
        },
        {
          "book": "bovada",
          "home_point": -1.5,
          "away_point": 1.5
        }
      ]
    },
    {
      "id": "fa294eb768832d8c8870b2c0559291c1",
      "sport": "MLB",
      "sport_key": "baseball_mlb",
      "home": "Washington Nationals",
      "away": "Kansas City Royals",
      "start_time": "2026-06-16T06:46:00+08:00",
      "commence_time_utc": "2026-06-15T22:46:00Z",
      "odds_h2h": [
        {
          "book": "fanduel",
          "home": 1.77,
          "away": 2.1,
          "draw": null
        }
      ],
      "odds_totals": [
        {
          "book": "fanduel",
          "line": 9.0,
          "over": 1.87,
          "under": 1.95
        }
      ],
      "odds_spreads": [
        {
          "book": "fanduel",
          "home_point": -1.5,
          "away_point": 1.5
        }
      ]
    },
    {
      "id": "6b47a66c52d27dacd1c7bbcd808713c1",
      "sport": "MLB",
      "sport_key": "baseball_mlb",
      "home": "Cincinnati Reds",
      "away": "New York Mets",
      "start_time": "2026-06-16T07:11:00+08:00",
      "commence_time_utc": "2026-06-15T23:11:00Z",
      "odds_h2h": [
        {
          "book": "fanduel",
          "home": 1.75,
          "away": 2.16,
          "draw": null
        }
      ],
      "odds_totals": [
        {
          "book": "fanduel",
          "line": 8.5,
          "over": 1.91,
          "under": 1.91
        }
      ],
      "odds_spreads": [
        {
          "book": "fanduel",
          "home_point": -1.5,
          "away_point": 1.5
        }
      ]
    },
    {
      "id": "d5349ae869ae1b1c6c38042687a3e57b",
      "sport": "MLB",
      "sport_key": "baseball_mlb",
      "home": "Houston Astros",
      "away": "Detroit Tigers",
      "start_time": "2026-06-16T08:11:00+08:00",
      "commence_time_utc": "2026-06-16T00:11:00Z",
      "odds_h2h": [
        {
          "book": "fanduel",
          "home": 1.77,
          "away": 2.1,
          "draw": null
        },
        {
          "book": "betonlineag",
          "home": 1.73,
          "away": 2.24,
          "draw": null
        },
        {
          "book": "lowvig",
          "home": 1.73,
          "away": 2.24,
          "draw": null
        },
        {
          "book": "betus",
          "home": 1.73,
          "away": 2.24,
          "draw": null
        },
        {
          "book": "betmgm",
          "home": 1.71,
          "away": 2.15,
          "draw": null
        },
        {
          "book": "draftkings",
          "home": 1.74,
          "away": 2.13,
          "draw": null
        },
        {
          "book": "bovada",
          "home": 1.74,
          "away": 2.13,
          "draw": null
        }
      ],
      "odds_totals": [
        {
          "book": "fanduel",
          "line": 8.5,
          "over": 1.81,
          "under": 2.02
        },
        {
          "book": "betonlineag",
          "line": 8.0,
          "over": 1.77,
          "under": 2.1
        },
        {
          "book": "lowvig",
          "line": 8.0,
          "over": 1.78,
          "under": 2.12
        },
        {
          "book": "betus",
          "line": 8.0,
          "over": 1.77,
          "under": 2.1
        },
        {
          "book": "betmgm",
          "line": 8.5,
          "over": 1.87,
          "under": 1.95
        },
        {
          "book": "draftkings",
          "line": 8.5,
          "over": 1.85,
          "under": 1.98
        },
        {
          "book": "bovada",
          "line": 8.5,
          "over": 1.8,
          "under": 2.05
        }
      ],
      "odds_spreads": [
        {
          "book": "fanduel",
          "home_point": 1.5,
          "away_point": -1.5
        },
        {
          "book": "betmgm",
          "home_point": -1.5,
          "away_point": 1.5
        },
        {
          "book": "draftkings",
          "home_point": -1.5,
          "away_point": 1.5
        },
        {
          "book": "bovada",
          "home_point": -1.5,
          "away_point": 1.5
        }
      ]
    },
    {
      "id": "38a1ef501107d0410c8595f25612567d",
      "sport": "MLB",
      "sport_key": "baseball_mlb",
      "home": "Arizona Diamondbacks",
      "away": "Los Angeles Angels",
      "start_time": "2026-06-16T09:41:00+08:00",
      "commence_time_utc": "2026-06-16T01:41:00Z",
      "odds_h2h": [
        {
          "book": "fanduel",
          "home": 1.75,
          "away": 2.14,
          "draw": null
        },
        {
          "book": "betonlineag",
          "home": 1.84,
          "away": 2.08,
          "draw": null
        },
        {
          "book": "lowvig",
          "home": 1.84,
          "away": 2.08,
          "draw": null
        },
        {
          "book": "betmgm",
          "home": 1.77,
          "away": 2.05,
          "draw": null
        },
        {
          "book": "draftkings",
          "home": 1.82,
          "away": 2.02,
          "draw": null
        },
        {
          "book": "betus",
          "home": 1.85,
          "away": 2.08,
          "draw": null
        },
        {
          "book": "bovada",
          "home": 1.83,
          "away": 2.0,
          "draw": null
        }
      ],
      "odds_totals": [
        {
          "book": "fanduel",
          "line": 9.0,
          "over": 1.95,
          "under": 1.87
        },
        {
          "book": "betonlineag",
          "line": 8.5,
          "over": 1.77,
          "under": 2.1
        },
        {
          "book": "lowvig",
          "line": 8.5,
          "over": 1.78,
          "under": 2.12
        },
        {
          "book": "betmgm",
          "line": 9.0,
          "over": 2.0,
          "under": 1.83
        },
        {
          "book": "draftkings",
          "line": 9.0,
          "over": 1.93,
          "under": 1.89
        },
        {
          "book": "betus",
          "line": 8.5,
          "over": 1.77,
          "under": 2.1
        },
        {
          "book": "bovada",
          "line": 9.0,
          "over": 1.87,
          "under": 1.95
        }
      ],
      "odds_spreads": [
        {
          "book": "fanduel",
          "home_point": -1.5,
          "away_point": 1.5
        },
        {
          "book": "betmgm",
          "home_point": -1.5,
          "away_point": 1.5
        },
        {
          "book": "draftkings",
          "home_point": -1.5,
          "away_point": 1.5
        },
        {
          "book": "bovada",
          "home_point": 1.5,
          "away_point": -1.5
        }
      ]
    },
    {
      "id": "8e54fa4eee405d90f575942ad15b1d52",
      "sport": "MLB",
      "sport_key": "baseball_mlb",
      "home": "Athletics",
      "away": "Pittsburgh Pirates",
      "start_time": "2026-06-16T09:41:00+08:00",
      "commence_time_utc": "2026-06-16T01:41:00Z",
      "odds_h2h": [
        {
          "book": "fanduel",
          "home": 1.82,
          "away": 2.04,
          "draw": null
        },
        {
          "book": "lowvig",
          "home": 1.8,
          "away": 2.13,
          "draw": null
        },
        {
          "book": "betonlineag",
          "home": 1.8,
          "away": 2.13,
          "draw": null
        },
        {
          "book": "betus",
          "home": 1.8,
          "away": 2.14,
          "draw": null
        },
        {
          "book": "betmgm",
          "home": 1.74,
          "away": 2.1,
          "draw": null
        },
        {
          "book": "draftkings",
          "home": 1.76,
          "away": 2.09,
          "draw": null
        },
        {
          "book": "bovada",
          "home": 1.79,
          "away": 2.06,
          "draw": null
        }
      ],
      "odds_totals": [
        {
          "book": "fanduel",
          "line": 10.5,
          "over": 1.81,
          "under": 2.02
        },
        {
          "book": "lowvig",
          "line": 10.0,
          "over": 1.81,
          "under": 2.07
        },
        {
          "book": "betonlineag",
          "line": 10.0,
          "over": 1.8,
          "under": 2.05
        },
        {
          "book": "betus",
          "line": 10.0,
          "over": 1.8,
          "under": 2.05
        },
        {
          "book": "betmgm",
          "line": 10.5,
          "over": 1.87,
          "under": 1.95
        },
        {
          "book": "draftkings",
          "line": 10.5,
          "over": 1.85,
          "under": 1.98
        },
        {
          "book": "bovada",
          "line": 11.0,
          "over": 2.0,
          "under": 1.83
        }
      ],
      "odds_spreads": [
        {
          "book": "fanduel",
          "home_point": 1.5,
          "away_point": -1.5
        },
        {
          "book": "betmgm",
          "home_point": -1.5,
          "away_point": 1.5
        },
        {
          "book": "draftkings",
          "home_point": -1.5,
          "away_point": 1.5
        },
        {
          "book": "bovada",
          "home_point": -1.5,
          "away_point": 1.5
        }
      ]
    },
    {
      "id": "da125dfa2d7fe97d5836e50dd394db59",
      "sport": "MLB",
      "sport_key": "baseball_mlb",
      "home": "Los Angeles Dodgers",
      "away": "Tampa Bay Rays",
      "start_time": "2026-06-16T10:11:00+08:00",
      "commence_time_utc": "2026-06-16T02:11:00Z",
      "odds_h2h": [
        {
          "book": "fanduel",
          "home": 1.6,
          "away": 2.42,
          "draw": null
        },
        {
          "book": "lowvig",
          "home": 1.66,
          "away": 2.38,
          "draw": null
        },
        {
          "book": "betonlineag",
          "home": 1.66,
          "away": 2.38,
          "draw": null
        },
        {
          "book": "betmgm",
          "home": 1.61,
          "away": 2.35,
          "draw": null
        },
        {
          "book": "draftkings",
          "home": 1.61,
          "away": 2.35,
          "draw": null
        },
        {
          "book": "betus",
          "home": 1.66,
          "away": 2.36,
          "draw": null
        },
        {
          "book": "bovada",
          "home": 1.61,
          "away": 2.39,
          "draw": null
        }
      ],
      "odds_totals": [
        {
          "book": "fanduel",
          "line": 9.0,
          "over": 1.94,
          "under": 1.88
        },
        {
          "book": "lowvig",
          "line": 8.5,
          "over": 1.85,
          "under": 2.03
        },
        {
          "book": "betonlineag",
          "line": 8.5,
          "over": 1.83,
          "under": 2.0
        },
        {
          "book": "betmgm",
          "line": 8.5,
          "over": 1.83,
          "under": 2.0
        },
        {
          "book": "draftkings",
          "line": 9.0,
          "over": 2.01,
          "under": 1.82
        },
        {
          "book": "betus",
          "line": 8.5,
          "over": 1.83,
          "under": 2.0
        },
        {
          "book": "bovada",
          "line": 9.0,
          "over": 2.0,
          "under": 1.83
        }
      ],
      "odds_spreads": [
        {
          "book": "fanduel",
          "home_point": -1.5,
          "away_point": 1.5
        },
        {
          "book": "betmgm",
          "home_point": -1.5,
          "away_point": 1.5
        },
        {
          "book": "draftkings",
          "home_point": -1.5,
          "away_point": 1.5
        },
        {
          "book": "bovada",
          "home_point": -1.5,
          "away_point": 1.5
        }
      ]
    },
    {
      "id": "05752bb341e197001387b64f3a06b9b2",
      "sport": "FIFA",
      "sport_key": "soccer_fifa_world_cup",
      "home": "Ivory Coast",
      "away": "Ecuador",
      "start_time": "2026-06-15T07:00:00+08:00",
      "commence_time_utc": "2026-06-14T23:00:00Z",
      "odds_h2h": [
        {
          "book": "fanduel",
          "home": 3.4,
          "away": 2.45,
          "draw": 2.85
        },
        {
          "book": "betmgm",
          "home": 3.25,
          "away": 2.45,
          "draw": 2.85
        },
        {
          "book": "bovada",
          "home": 3.4,
          "away": 2.42,
          "draw": 2.85
        },
        {
          "book": "betonlineag",
          "home": 3.38,
          "away": 2.53,
          "draw": 2.95
        },
        {
          "book": "mybookieag",
          "home": 3.3,
          "away": 2.47,
          "draw": 2.84
        },
        {
          "book": "draftkings",
          "home": 3.45,
          "away": 2.45,
          "draw": 2.9
        },
        {
          "book": "betrivers",
          "home": 3.25,
          "away": 2.55,
          "draw": 2.85
        },
        {
          "book": "betus",
          "home": 3.5,
          "away": 2.4,
          "draw": 2.88
        },
        {
          "book": "lowvig",
          "home": 3.38,
          "away": 2.53,
          "draw": 2.95
        }
      ],
      "odds_totals": [
        {
          "book": "betmgm",
          "line": 1.5,
          "over": 1.62,
          "under": 2.35
        },
        {
          "book": "bovada",
          "line": 1.75,
          "over": 1.8,
          "under": 2.05
        },
        {
          "book": "betonlineag",
          "line": 2.0,
          "over": 2.23,
          "under": 1.71
        },
        {
          "book": "mybookieag",
          "line": 2.0,
          "over": 2.15,
          "under": 1.71
        },
        {
          "book": "betrivers",
          "line": 1.5,
          "over": 1.55,
          "under": 2.4
        },
        {
          "book": "betus",
          "line": 2.0,
          "over": 2.2,
          "under": 1.71
        },
        {
          "book": "lowvig",
          "line": 2.0,
          "over": 2.23,
          "under": 1.71
        }
      ],
      "odds_spreads": [
        {
          "book": "bovada",
          "home_point": 0.25,
          "away_point": -0.25
        },
        {
          "book": "betonlineag",
          "home_point": 0.0,
          "away_point": 0.0
        },
        {
          "book": "mybookieag",
          "home_point": 0.0,
          "away_point": 0.0
        },
        {
          "book": "betus",
          "home_point": 0.0,
          "away_point": 0.0
        },
        {
          "book": "lowvig",
          "home_point": 0.0,
          "away_point": 0.0
        }
      ]
    },
    {
      "id": "b55f9569de3f4d731bc5537ff5ff43e4",
      "sport": "FIFA",
      "sport_key": "soccer_fifa_world_cup",
      "home": "Sweden",
      "away": "Tunisia",
      "start_time": "2026-06-15T10:00:00+08:00",
      "commence_time_utc": "2026-06-15T02:00:00Z",
      "odds_h2h": [
        {
          "book": "fanduel",
          "home": 1.87,
          "away": 4.6,
          "draw": 3.3
        },
        {
          "book": "betmgm",
          "home": 1.87,
          "away": 4.2,
          "draw": 3.3
        },
        {
          "book": "betonlineag",
          "home": 1.93,
          "away": 4.65,
          "draw": 3.38
        },
        {
          "book": "bovada",
          "home": 1.88,
          "away": 4.4,
          "draw": 3.4
        },
        {
          "book": "mybookieag",
          "home": 1.9,
          "away": 4.2,
          "draw": 3.36
        },
        {
          "book": "draftkings",
          "home": 1.91,
          "away": 4.5,
          "draw": 3.4
        },
        {
          "book": "betrivers",
          "home": 1.85,
          "away": 4.5,
          "draw": 3.45
        },
        {
          "book": "betus",
          "home": 1.91,
          "away": 4.4,
          "draw": 3.4
        },
        {
          "book": "lowvig",
          "home": 1.93,
          "away": 4.65,
          "draw": 3.38
        }
      ],
      "odds_totals": [
        {
          "book": "betmgm",
          "line": 2.5,
          "over": 2.2,
          "under": 1.69
        },
        {
          "book": "betonlineag",
          "line": 2.0,
          "over": 1.66,
          "under": 2.34
        },
        {
          "book": "bovada",
          "line": 2.5,
          "over": 2.2,
          "under": 1.69
        },
        {
          "book": "mybookieag",
          "line": 2.5,
          "over": 2.16,
          "under": 1.7
        },
        {
          "book": "betrivers",
          "line": 2.5,
          "over": 2.14,
          "under": 1.68
        },
        {
          "book": "betus",
          "line": 2.5,
          "over": 2.2,
          "under": 1.71
        },
        {
          "book": "lowvig",
          "line": 2.0,
          "over": 1.66,
          "under": 2.34
        }
      ],
      "odds_spreads": [
        {
          "book": "betonlineag",
          "home_point": -0.5,
          "away_point": 0.5
        },
        {
          "book": "bovada",
          "home_point": -0.5,
          "away_point": 0.5
        },
        {
          "book": "mybookieag",
          "home_point": -0.5,
          "away_point": 0.5
        },
        {
          "book": "betus",
          "home_point": -0.5,
          "away_point": 0.5
        },
        {
          "book": "lowvig",
          "home_point": -0.5,
          "away_point": 0.5
        }
      ]
    },
    {
      "id": "c54f00b11925751d2b62988775c6c239",
      "sport": "FIFA",
      "sport_key": "soccer_fifa_world_cup",
      "home": "Spain",
      "away": "Cape Verde",
      "start_time": "2026-06-16T00:00:00+08:00",
      "commence_time_utc": "2026-06-15T16:00:00Z",
      "odds_h2h": [
        {
          "book": "betmgm",
          "home": 1.1,
          "away": 23.0,
          "draw": 10.0
        },
        {
          "book": "fanduel",
          "home": 1.07,
          "away": 23.0,
          "draw": 15.0
        },
        {
          "book": "bovada",
          "home": 1.08,
          "away": 23.0,
          "draw": 12.0
        },
        {
          "book": "betonlineag",
          "home": 1.1,
          "away": 26.0,
          "draw": 12.0
        },
        {
          "book": "mybookieag",
          "home": 1.07,
          "away": 29.55,
          "draw": 11.36
        },
        {
          "book": "draftkings",
          "home": 1.09,
          "away": 23.0,
          "draw": 12.0
        },
        {
          "book": "betrivers",
          "home": 1.09,
          "away": 26.0,
          "draw": 11.5
        },
        {
          "book": "betus",
          "home": 1.08,
          "away": 29.0,
          "draw": 11.25
        },
        {
          "book": "lowvig",
          "home": 1.1,
          "away": 26.0,
          "draw": 12.0
        }
      ],
      "odds_totals": [
        {
          "book": "betmgm",
          "line": 3.5,
          "over": 1.98,
          "under": 1.87
        },
        {
          "book": "bovada",
          "line": 3.5,
          "over": 1.91,
          "under": 1.91
        },
        {
          "book": "betonlineag",
          "line": 3.5,
          "over": 1.99,
          "under": 1.87
        },
        {
          "book": "mybookieag",
          "line": 3.5,
          "over": 1.94,
          "under": 1.87
        },
        {
          "book": "betrivers",
          "line": 3.5,
          "over": 1.87,
          "under": 1.88
        },
        {
          "book": "betus",
          "line": 3.5,
          "over": 1.95,
          "under": 1.87
        },
        {
          "book": "lowvig",
          "line": 3.5,
          "over": 1.99,
          "under": 1.87
        }
      ],
      "odds_spreads": [
        {
          "book": "bovada",
          "home_point": -2.5,
          "away_point": 2.5
        },
        {
          "book": "betonlineag",
          "home_point": -2.5,
          "away_point": 2.5
        },
        {
          "book": "mybookieag",
          "home_point": -2.5,
          "away_point": 2.5
        },
        {
          "book": "betus",
          "home_point": -2.5,
          "away_point": 2.5
        },
        {
          "book": "lowvig",
          "home_point": -2.5,
          "away_point": 2.5
        }
      ]
    },
    {
      "id": "fbfb95c62003fd6d828b309f96ee1f9b",
      "sport": "FIFA",
      "sport_key": "soccer_fifa_world_cup",
      "home": "Belgium",
      "away": "Egypt",
      "start_time": "2026-06-16T03:00:00+08:00",
      "commence_time_utc": "2026-06-15T19:00:00Z",
      "odds_h2h": [
        {
          "book": "betmgm",
          "home": 1.62,
          "away": 5.25,
          "draw": 3.9
        },
        {
          "book": "fanduel",
          "home": 1.61,
          "away": 5.9,
          "draw": 3.9
        },
        {
          "book": "bovada",
          "home": 1.61,
          "away": 5.6,
          "draw": 3.95
        },
        {
          "book": "betonlineag",
          "home": 1.63,
          "away": 5.75,
          "draw": 4.05
        },
        {
          "book": "mybookieag",
          "home": 1.6,
          "away": 5.6,
          "draw": 3.9
        },
        {
          "book": "draftkings",
          "home": 1.61,
          "away": 5.5,
          "draw": 3.9
        },
        {
          "book": "betrivers",
          "home": 1.57,
          "away": 6.0,
          "draw": 4.0
        },
        {
          "book": "betus",
          "home": 1.61,
          "away": 5.65,
          "draw": 4.0
        },
        {
          "book": "lowvig",
          "home": 1.63,
          "away": 5.75,
          "draw": 4.05
        }
      ],
      "odds_totals": [
        {
          "book": "betmgm",
          "line": 2.5,
          "over": 2.0,
          "under": 1.83
        },
        {
          "book": "bovada",
          "line": 2.5,
          "over": 2.0,
          "under": 1.83
        },
        {
          "book": "betonlineag",
          "line": 2.5,
          "over": 2.01,
          "under": 1.85
        },
        {
          "book": "mybookieag",
          "line": 2.5,
          "over": 2.0,
          "under": 1.82
        },
        {
          "book": "betrivers",
          "line": 2.5,
          "over": 1.93,
          "under": 1.83
        },
        {
          "book": "betus",
          "line": 2.5,
          "over": 2.0,
          "under": 1.83
        },
        {
          "book": "lowvig",
          "line": 2.5,
          "over": 2.01,
          "under": 1.85
        }
      ],
      "odds_spreads": [
        {
          "book": "bovada",
          "home_point": -0.75,
          "away_point": 0.75
        },
        {
          "book": "betonlineag",
          "home_point": -1.0,
          "away_point": 1.0
        },
        {
          "book": "mybookieag",
          "home_point": -1.0,
          "away_point": 1.0
        },
        {
          "book": "betus",
          "home_point": -1.0,
          "away_point": 1.0
        },
        {
          "book": "lowvig",
          "home_point": -1.0,
          "away_point": 1.0
        }
      ]
    },
    {
      "id": "64b91c5f2db61c7358a4f05459e83c52",
      "sport": "FIFA",
      "sport_key": "soccer_fifa_world_cup",
      "home": "Saudi Arabia",
      "away": "Uruguay",
      "start_time": "2026-06-16T06:00:00+08:00",
      "commence_time_utc": "2026-06-15T22:00:00Z",
      "odds_h2h": [
        {
          "book": "betmgm",
          "home": 7.0,
          "away": 1.45,
          "draw": 4.33
        },
        {
          "book": "fanduel",
          "home": 7.0,
          "away": 1.48,
          "draw": 4.2
        },
        {
          "book": "bovada",
          "home": 7.25,
          "away": 1.47,
          "draw": 4.2
        },
        {
          "book": "betonlineag",
          "home": 7.95,
          "away": 1.47,
          "draw": 4.38
        },
        {
          "book": "mybookieag",
          "home": 7.17,
          "away": 1.45,
          "draw": 4.36
        },
        {
          "book": "draftkings",
          "home": 7.5,
          "away": 1.47,
          "draw": 4.4
        },
        {
          "book": "betrivers",
          "home": 8.0,
          "away": 1.43,
          "draw": 4.35
        },
        {
          "book": "betus",
          "home": 7.45,
          "away": 1.48,
          "draw": 4.25
        },
        {
          "book": "lowvig",
          "home": 7.95,
          "away": 1.47,
          "draw": 4.38
        }
      ],
      "odds_totals": [
        {
          "book": "betmgm",
          "line": 2.5,
          "over": 2.05,
          "under": 1.77
        },
        {
          "book": "bovada",
          "line": 2.25,
          "over": 1.83,
          "under": 2.0
        },
        {
          "book": "betonlineag",
          "line": 2.5,
          "over": 2.12,
          "under": 1.78
        },
        {
          "book": "mybookieag",
          "line": 2.5,
          "over": 2.0,
          "under": 1.83
        },
        {
          "book": "betrivers",
          "line": 2.5,
          "over": 1.95,
          "under": 1.81
        },
        {
          "book": "betus",
          "line": 2.5,
          "over": 2.0,
          "under": 1.83
        },
        {
          "book": "lowvig",
          "line": 2.5,
          "over": 2.12,
          "under": 1.78
        }
      ],
      "odds_spreads": [
        {
          "book": "bovada",
          "home_point": 1.0,
          "away_point": -1.0
        },
        {
          "book": "betonlineag",
          "home_point": 1.0,
          "away_point": -1.0
        },
        {
          "book": "mybookieag",
          "home_point": 1.0,
          "away_point": -1.0
        },
        {
          "book": "betus",
          "home_point": 1.0,
          "away_point": -1.0
        },
        {
          "book": "lowvig",
          "home_point": 1.0,
          "away_point": -1.0
        }
      ]
    },
    {
      "id": "ec51b9c44ad5e34552f3ab53f7262813",
      "sport": "FIFA",
      "sport_key": "soccer_fifa_world_cup",
      "home": "Iran",
      "away": "New Zealand",
      "start_time": "2026-06-16T09:00:00+08:00",
      "commence_time_utc": "2026-06-16T01:00:00Z",
      "odds_h2h": [
        {
          "book": "betmgm",
          "home": 1.91,
          "away": 4.2,
          "draw": 3.25
        },
        {
          "book": "fanduel",
          "home": 1.91,
          "away": 4.5,
          "draw": 3.3
        },
        {
          "book": "bovada",
          "home": 1.93,
          "away": 4.25,
          "draw": 3.3
        },
        {
          "book": "betonlineag",
          "home": 1.93,
          "away": 4.51,
          "draw": 3.4
        },
        {
          "book": "mybookieag",
          "home": 1.9,
          "away": 4.4,
          "draw": 3.26
        },
        {
          "book": "draftkings",
          "home": 1.95,
          "away": 4.3,
          "draw": 3.4
        },
        {
          "book": "betrivers",
          "home": 1.87,
          "away": 4.6,
          "draw": 3.35
        },
        {
          "book": "betus",
          "home": 1.91,
          "away": 4.5,
          "draw": 3.4
        },
        {
          "book": "lowvig",
          "home": 1.93,
          "away": 4.51,
          "draw": 3.4
        }
      ],
      "odds_totals": [
        {
          "book": "betmgm",
          "line": 2.5,
          "over": 2.5,
          "under": 1.57
        },
        {
          "book": "bovada",
          "line": 2.0,
          "over": 1.83,
          "under": 2.0
        },
        {
          "book": "betonlineag",
          "line": 2.0,
          "over": 1.85,
          "under": 2.02
        },
        {
          "book": "mybookieag",
          "line": 2.0,
          "over": 1.74,
          "under": 1.98
        },
        {
          "book": "betrivers",
          "line": 2.5,
          "over": 2.3,
          "under": 1.57
        },
        {
          "book": "betus",
          "line": 2.0,
          "over": 1.83,
          "under": 2.0
        },
        {
          "book": "lowvig",
          "line": 2.0,
          "over": 1.85,
          "under": 2.02
        }
      ],
      "odds_spreads": [
        {
          "book": "bovada",
          "home_point": -0.5,
          "away_point": 0.5
        },
        {
          "book": "betonlineag",
          "home_point": -0.5,
          "away_point": 0.5
        },
        {
          "book": "mybookieag",
          "home_point": -0.5,
          "away_point": 0.5
        },
        {
          "book": "betus",
          "home_point": -0.5,
          "away_point": 0.5
        },
        {
          "book": "lowvig",
          "home_point": -0.5,
          "away_point": 0.5
        }
      ]
    },
    {
      "id": "73a4fcd14cc9766b9b9bfd50b8ca153a",
      "sport": "FIFA",
      "sport_key": "soccer_fifa_world_cup",
      "home": "France",
      "away": "Senegal",
      "start_time": "2026-06-17T03:00:00+08:00",
      "commence_time_utc": "2026-06-16T19:00:00Z",
      "odds_h2h": [
        {
          "book": "betmgm",
          "home": 1.48,
          "away": 6.25,
          "draw": 4.5
        },
        {
          "book": "fanduel",
          "home": 1.45,
          "away": 7.0,
          "draw": 4.4
        },
        {
          "book": "bovada",
          "home": 1.46,
          "away": 7.0,
          "draw": 4.4
        },
        {
          "book": "betonlineag",
          "home": 1.47,
          "away": 7.75,
          "draw": 4.48
        },
        {
          "book": "mybookieag",
          "home": 1.45,
          "away": 7.06,
          "draw": 4.46
        },
        {
          "book": "draftkings",
          "home": 1.48,
          "away": 7.0,
          "draw": 4.4
        },
        {
          "book": "betrivers",
          "home": 1.45,
          "away": 7.5,
          "draw": 4.35
        },
        {
          "book": "betus",
          "home": 1.47,
          "away": 7.2,
          "draw": 4.4
        },
        {
          "book": "lowvig",
          "home": 1.47,
          "away": 7.75,
          "draw": 4.48
        }
      ],
      "odds_totals": [
        {
          "book": "betmgm",
          "line": 2.5,
          "over": 1.91,
          "under": 1.91
        },
        {
          "book": "bovada",
          "line": 2.5,
          "over": 1.95,
          "under": 1.87
        },
        {
          "book": "betonlineag",
          "line": 2.5,
          "over": 1.94,
          "under": 1.91
        },
        {
          "book": "mybookieag",
          "line": 2.5,
          "over": 1.88,
          "under": 1.83
        },
        {
          "book": "betrivers",
          "line": 2.5,
          "over": 1.85,
          "under": 1.91
        },
        {
          "book": "betus",
          "line": 2.5,
          "over": 1.95,
          "under": 1.87
        },
        {
          "book": "lowvig",
          "line": 2.5,
          "over": 1.94,
          "under": 1.91
        }
      ],
      "odds_spreads": [
        {
          "book": "bovada",
          "home_point": -1.0,
          "away_point": 1.0
        },
        {
          "book": "betonlineag",
          "home_point": -1.0,
          "away_point": 1.0
        },
        {
          "book": "mybookieag",
          "home_point": -1.0,
          "away_point": 1.0
        },
        {
          "book": "betus",
          "home_point": -1.0,
          "away_point": 1.0
        },
        {
          "book": "lowvig",
          "home_point": -1.0,
          "away_point": 1.0
        }
      ]
    },
    {
      "id": "4d4f2b9b78182b557d4fbf8dcf4f4af2",
      "sport": "FIFA",
      "sport_key": "soccer_fifa_world_cup",
      "home": "Iraq",
      "away": "Norway",
      "start_time": "2026-06-17T06:00:00+08:00",
      "commence_time_utc": "2026-06-16T22:00:00Z",
      "odds_h2h": [
        {
          "book": "betmgm",
          "home": 13.0,
          "away": 1.2,
          "draw": 6.75
        },
        {
          "book": "betonlineag",
          "home": 15.0,
          "away": 1.2,
          "draw": 7.55
        },
        {
          "book": "fanduel",
          "home": 15.0,
          "away": 1.17,
          "draw": 7.0
        },
        {
          "book": "bovada",
          "home": 14.0,
          "away": 1.18,
          "draw": 7.25
        },
        {
          "book": "mybookieag",
          "home": 14.25,
          "away": 1.18,
          "draw": 6.8
        },
        {
          "book": "draftkings",
          "home": 15.0,
          "away": 1.19,
          "draw": 7.0
        },
        {
          "book": "betrivers",
          "home": 15.0,
          "away": 1.19,
          "draw": 7.0
        },
        {
          "book": "betus",
          "home": 14.3,
          "away": 1.19,
          "draw": 7.25
        },
        {
          "book": "lowvig",
          "home": 15.0,
          "away": 1.2,
          "draw": 7.55
        }
      ],
      "odds_totals": [
        {
          "book": "betmgm",
          "line": 2.5,
          "over": 1.61,
          "under": 2.4
        },
        {
          "book": "betonlineag",
          "line": 3.0,
          "over": 1.88,
          "under": 1.98
        },
        {
          "book": "bovada",
          "line": 3.0,
          "over": 1.98,
          "under": 1.85
        },
        {
          "book": "mybookieag",
          "line": 3.0,
          "over": 1.88,
          "under": 1.83
        },
        {
          "book": "betrivers",
          "line": 3.5,
          "over": 2.35,
          "under": 1.56
        },
        {
          "book": "betus",
          "line": 3.0,
          "over": 1.95,
          "under": 1.87
        },
        {
          "book": "lowvig",
          "line": 3.0,
          "over": 1.88,
          "under": 1.98
        }
      ],
      "odds_spreads": [
        {
          "book": "betonlineag",
          "home_point": 2.0,
          "away_point": -2.0
        },
        {
          "book": "bovada",
          "home_point": 2.0,
          "away_point": -2.0
        },
        {
          "book": "mybookieag",
          "home_point": 2.0,
          "away_point": -2.0
        },
        {
          "book": "betus",
          "home_point": 2.0,
          "away_point": -2.0
        },
        {
          "book": "lowvig",
          "home_point": 2.0,
          "away_point": -2.0
        }
      ]
    }
  ],
  "updated_at": "2026-06-15T06:05:06+08:00"
}